{
    "type": "DecisionNode",
    "state": 4,
    "visits": 1000,
    "value": -510.87999999999715,
    "children": {
        "2": {
            "type": "ChanceNode",
            "action_id": 2,
            "visits": 126,
            "value": -78.48000000000002,
            "children": {
                "8": {
                    "type": "DecisionNode",
                    "state": 8,
                    "visits": 42,
                    "value": -27.150000000000006,
                    "children": {
                        "0": {
                            "type": "ChanceNode",
                            "action_id": 0,
                            "visits": 8,
                            "value": -6.02,
                            "children": "Max depth reached"
                        },
                        "3": {
                            "type": "ChanceNode",
                            "action_id": 3,
                            "visits": 15,
                            "value": -8.069999999999999,
                            "children": "Max depth reached"
                        },
                        "1": {
                            "type": "ChanceNode",
                            "action_id": 1,
                            "visits": 8,
                            "value": -6.02,
                            "children": "Max depth reached"
                        },
                        "2": {
                            "type": "ChanceNode",
                            "action_id": 2,
                            "visits": 10,
                            "value": -7.029999999999999,
                            "children": "Max depth reached"
                        }
                    }
                },
                "0": {
                    "type": "DecisionNode",
                    "state": 0,
                    "visits": 41,
                    "value": -8.329999999999995,
                    "children": {
                        "1": {
                            "type": "ChanceNode",
                            "action_id": 1,
                            "visits": 7,
                            "value": -3.0399999999999996,
                            "children": "Max depth reached"
                        },
                        "0": {
                            "type": "ChanceNode",
                            "action_id": 0,
                            "visits": 8,
                            "value": -3.05,
                            "children": "Max depth reached"
                        },
                        "2": {
                            "type": "ChanceNode",
                            "action_id": 2,
                            "visits": 13,
                            "value": -1.12,
                            "children": "Max depth reached"
                        },
                        "3": {
                            "type": "ChanceNode",
                            "action_id": 3,
                            "visits": 13,
                            "value": -1.12,
                            "children": "Max depth reached"
                        }
                    }
                },
                "5": {
                    "type": "DecisionNode",
                    "state": 5,
                    "visits": 43,
                    "value": -43.0,
                    "children": {}
                }
            }
        },
        "3": {
            "type": "ChanceNode",
            "action_id": 3,
            "visits": 186,
            "value": -104.82000000000019,
            "children": {
                "5": {
                    "type": "DecisionNode",
                    "state": 5,
                    "visits": 57,
                    "value": -57.0,
                    "children": {}
                },
                "0": {
                    "type": "DecisionNode",
                    "state": 0,
                    "visits": 68,
                    "value": -23.450000000000028,
                    "children": {
                        "3": {
                            "type": "ChanceNode",
                            "action_id": 3,
                            "visits": 19,
                            "value": -6.129999999999999,
                            "children": "Max depth reached"
                        },
                        "1": {
                            "type": "ChanceNode",
                            "action_id": 1,
                            "visits": 11,
                            "value": -6.05,
                            "children": "Max depth reached"
                        },
                        "0": {
                            "type": "ChanceNode",
                            "action_id": 0,
                            "visits": 25,
                            "value": -5.199999999999996,
                            "children": "Max depth reached"
                        },
                        "2": {
                            "type": "ChanceNode",
                            "action_id": 2,
                            "visits": 13,
                            "value": -6.0699999999999985,
                            "children": "Max depth reached"
                        }
                    }
                },
                "4": {
                    "type": "DecisionNode",
                    "state": 4,
                    "visits": 61,
                    "value": -24.37,
                    "children": {
                        "0": {
                            "type": "ChanceNode",
                            "action_id": 0,
                            "visits": 27,
                            "value": -6.209999999999998,
                            "children": "Max depth reached"
                        },
                        "2": {
                            "type": "ChanceNode",
                            "action_id": 2,
                            "visits": 14,
                            "value": -6.079999999999998,
                            "children": "Max depth reached"
                        },
                        "3": {
                            "type": "ChanceNode",
                            "action_id": 3,
                            "visits": 13,
                            "value": -6.069999999999999,
                            "children": "Max depth reached"
                        },
                        "1": {
                            "type": "ChanceNode",
                            "action_id": 1,
                            "visits": 7,
                            "value": -6.01,
                            "children": "Max depth reached"
                        }
                    }
                }
            }
        },
        "0": {
            "type": "ChanceNode",
            "action_id": 0,
            "visits": 580,
            "value": -257.1999999999988,
            "children": {
                "8": {
                    "type": "DecisionNode",
                    "state": 8,
                    "visits": 191,
                    "value": -110.75000000000014,
                    "children": {
                        "0": {
                            "type": "ChanceNode",
                            "action_id": 0,
                            "visits": 31,
                            "value": -22.090000000000003,
                            "children": "Max depth reached"
                        },
                        "1": {
                            "type": "ChanceNode",
                            "action_id": 1,
                            "visits": 49,
                            "value": -28.210000000000008,
                            "children": "Max depth reached"
                        },
                        "3": {
                            "type": "ChanceNode",
                            "action_id": 3,
                            "visits": 70,
                            "value": -35.33000000000001,
                            "children": "Max depth reached"
                        },
                        "2": {
                            "type": "ChanceNode",
                            "action_id": 2,
                            "visits": 40,
                            "value": -25.110000000000007,
                            "children": "Max depth reached"
                        }
                    }
                },
                "4": {
                    "type": "DecisionNode",
                    "state": 4,
                    "visits": 187,
                    "value": -84.04000000000006,
                    "children": {
                        "2": {
                            "type": "ChanceNode",
                            "action_id": 2,
                            "visits": 48,
                            "value": -22.26000000000001,
                            "children": "Max depth reached"
                        },
                        "1": {
                            "type": "ChanceNode",
                            "action_id": 1,
                            "visits": 32,
                            "value": -18.140000000000004,
                            "children": "Max depth reached"
                        },
                        "0": {
                            "type": "ChanceNode",
                            "action_id": 0,
                            "visits": 84,
                            "value": -28.560000000000034,
                            "children": "Max depth reached"
                        },
                        "3": {
                            "type": "ChanceNode",
                            "action_id": 3,
                            "visits": 23,
                            "value": -15.079999999999998,
                            "children": "Max depth reached"
                        }
                    }
                },
                "0": {
                    "type": "DecisionNode",
                    "state": 0,
                    "visits": 202,
                    "value": -62.40999999999991,
                    "children": {
                        "1": {
                            "type": "ChanceNode",
                            "action_id": 1,
                            "visits": 40,
                            "value": -15.249999999999996,
                            "children": "Max depth reached"
                        },
                        "0": {
                            "type": "ChanceNode",
                            "action_id": 0,
                            "visits": 74,
                            "value": -17.56999999999999,
                            "children": "Max depth reached"
                        },
                        "2": {
                            "type": "ChanceNode",
                            "action_id": 2,
                            "visits": 41,
                            "value": -14.269999999999996,
                            "children": "Max depth reached"
                        },
                        "3": {
                            "type": "ChanceNode",
                            "action_id": 3,
                            "visits": 47,
                            "value": -15.319999999999995,
                            "children": "Max depth reached"
                        }
                    }
                }
            }
        },
        "1": {
            "type": "ChanceNode",
            "action_id": 1,
            "visits": 108,
            "value": -70.38000000000001,
            "children": {
                "4": {
                    "type": "DecisionNode",
                    "state": 4,
                    "visits": 34,
                    "value": -12.219999999999999,
                    "children": {
                        "2": {
                            "type": "ChanceNode",
                            "action_id": 2,
                            "visits": 9,
                            "value": -3.0599999999999996,
                            "children": "Max depth reached"
                        },
                        "3": {
                            "type": "ChanceNode",
                            "action_id": 3,
                            "visits": 8,
                            "value": -3.05,
                            "children": "Max depth reached"
                        },
                        "1": {
                            "type": "ChanceNode",
                            "action_id": 1,
                            "visits": 8,
                            "value": -3.05,
                            "children": "Max depth reached"
                        },
                        "0": {
                            "type": "ChanceNode",
                            "action_id": 0,
                            "visits": 8,
                            "value": -3.0499999999999994,
                            "children": "Max depth reached"
                        }
                    }
                },
                "5": {
                    "type": "DecisionNode",
                    "state": 5,
                    "visits": 35,
                    "value": -35.0,
                    "children": {}
                },
                "8": {
                    "type": "DecisionNode",
                    "state": 8,
                    "visits": 39,
                    "value": -23.16,
                    "children": {
                        "3": {
                            "type": "ChanceNode",
                            "action_id": 3,
                            "visits": 13,
                            "value": -6.069999999999999,
                            "children": "Max depth reached"
                        },
                        "2": {
                            "type": "ChanceNode",
                            "action_id": 2,
                            "visits": 8,
                            "value": -6.02,
                            "children": "Max depth reached"
                        },
                        "0": {
                            "type": "ChanceNode",
                            "action_id": 0,
                            "visits": 12,
                            "value": -6.059999999999999,
                            "children": "Max depth reached"
                        },
                        "1": {
                            "type": "ChanceNode",
                            "action_id": 1,
                            "visits": 6,
                            "value": -5.01,
                            "children": "Max depth reached"
                        }
                    }
                }
            }
        }
    }
}